{
    "maxim": {
      "dummy_example_max32650": {
        "flags" : "DUMMY_EXAMPLE=y IIO_EXAMPLE=n TARGET=max32650"
      },
      "iio_example_max32650": {
        "flags" : "DUMMY_EXAMPLE=n IIO_EXAMPLE=y TARGET=max32650"
      },
      "dummy_example_max32655": {
        "flags" : "DUMMY_EXAMPLE=y IIO_EXAMPLE=n TARGET=max32655"
      },
      "iio_example_max32655": {
        "flags" : "DUMMY_EXAMPLE=n IIO_EXAMPLE=y TARGET=max32655"
      },
      "dummy_example_max32660": {
        "flags" : "DUMMY_EXAMPLE=y IIO_EXAMPLE=n TARGET=max32660"
      },
      "iio_example_max32660": {
        "flags" : "DUMMY_EXAMPLE=n IIO_EXAMPLE=y TARGET=max32660"
      },
      "dummy_example_max32665": {
        "flags" : "DUMMY_EXAMPLE=y IIO_EXAMPLE=n TARGET=max32665"
      },
      "iio_example_max32665": {
        "flags" : "DUMMY_EXAMPLE=n IIO_EXAMPLE=y TARGET=max32665"
      },
      "dummy_example_max78000": {
        "flags" : "DUMMY_EXAMPLE=y IIO_EXAMPLE=n TARGET=max78000"
      },
      "iio_example_max78000": {
        "flags" : "DUMMY_EXAMPLE=n IIO_EXAMPLE=y TARGET=max78000"
      },
      "dummy_example_max32690": {
        "flags" : "DUMMY_EXAMPLE=y IIO_EXAMPLE=n TARGET=max32690"
      },
      "iio_example_max32690": {
        "flags" : "DUMMY_EXAMPLE=n IIO_EXAMPLE=y TARGET=max32690"
      }
    },
    "mbed": {
      "dummy_example_mbed": {
        "flags" : "DUMMY_EXAMPLE=y IIO_EXAMPLE=n"
      }
    }
}
